hrap/__init__.py
hrap/chamber.py
hrap/chem.py
hrap/core.py
hrap/fluid.py
hrap/grain.py
hrap/nozzle.py
hrap/sdf.py
hrap/tank.py
hrap/thermo.dat
hrap/units.py
hrap/gui/main.py
hrap/gui/themes.py
hrap/gui/frontend/.gitignore
hrap/gui/frontend/.vscode/settings.json
hrap/resources/icon.ico
hrap/resources/icon_16.png
hrap/resources/icon_24.png
hrap/resources/icon_32.png
hrap/resources/icon_48.png
hrap/resources/fonts/BubblegumSans-Regular.ttf
hrap/resources/fonts/BubblegumSans_OFL.txt
hrap/resources/fonts/Roboto-Regular.ttf
hrap/resources/fonts/Roboto_OFL.txt
hrap/resources/propellant_configs/ABS.mat
hrap/resources/propellant_configs/Asphalt.mat
hrap/resources/propellant_configs/HDPE.mat
hrap/resources/propellant_configs/HTPB.mat
hrap/resources/propellant_configs/HTPB_Paraffin.mat
hrap/resources/propellant_configs/Metalized_Plastisol.mat
hrap/resources/propellant_configs/Paraffin.mat
hrap/resources/propellant_configs/Sorbitol.mat
hrap/resources/validation/hybrid_fire_7_26_23.csv
hrap-0.1.7.dist-info/METADATA
hrap-0.1.7.dist-info/WHEEL
hrap-0.1.7.dist-info/entry_points.txt
hrap-0.1.7.dist-info/RECORD
