Metadata-Version: 2.4
Name: hrap
Version: 0.1.7
Summary: HRAP is a versatile tool for simulation of hybrid rocket engines.
Project-URL: Homepage, https://github.com/rnickel1/HRAP_Source
Author: Drew Nickel, Thomas A. Scott
Requires-Python: >=3.10
Requires-Dist: coolprop
Requires-Dist: dearpygui
Requires-Dist: dearpygui-ext
Requires-Dist: interpax
Requires-Dist: jax
Requires-Dist: jaxlib
Requires-Dist: numpy
Requires-Dist: scikit-image
Requires-Dist: scipy
